[
  {
    "id": "5df11255-d4fd-46a7-a76e-18663c715856",
    "roomNumber": "101",
    "type": "single",
    "price": 99,
    "isBooked": false,
    "guestName": null,
    "checkInDate": null,
    "checkOutDate": null,
    "amenities": [
      "Wi-Fi",
      "TV",
      "Air Conditioning"
    ],
    "description": "Comfortable single room with city view",
    "imageUrl": "https://images.unsplash.com/photo-1586023492125-27b2c045efd7?ixlib=rb-4.0.3&ixid=M3wxMjA3fDB8MHxwaG90by1wYWdlfHx8fGVufDB8fHx8fA%3D%3D&auto=format&fit=crop&w=1000&q=80",
    "createdAt": "2025-08-22T11:23:43.363Z",
    "updatedAt": "2025-08-22T11:36:13.790Z"
  },
  {
    "id": "3cbc6bf1-3761-4d88-9fdb-ca18a3d586a4",
    "roomNumber": "102",
    "type": "double",
    "price": 149,
    "isBooked": false,
    "guestName": null,
    "checkInDate": null,
    "checkOutDate": null,
    "amenities": [
      "Wi-Fi",
      "TV",
      "Air Conditioning",
      "Mini Bar"
    ],
    "description": "Spacious double room with garden view",
    "imageUrl": "https://images.unsplash.com/photo-1618773928121-c32242e63f39?ixlib=rb-4.0.3&ixid=M3wxMjA3fDB8MHxwaG90by1wYWdlfHx8fGVufDB8fHx8fA%3D%3D&auto=format&fit=crop&w=1000&q=80",
    "createdAt": "2025-08-22T11:23:43.363Z",
    "updatedAt": "2025-08-22T11:35:23.079Z"
  },
  {
    "id": "436ecd78-9225-4ff3-9d69-76f1943d8a41",
    "roomNumber": "201",
    "type": "suite",
    "price": 299,
    "isBooked": false,
    "guestName": null,
    "checkInDate": null,
    "checkOutDate": null,
    "amenities": [
      "Wi-Fi",
      "TV",
      "Air Conditioning",
      "Mini Bar",
      "Jacuzzi",
      "Balcony"
    ],
    "description": "Luxury suite with panoramic city view",
    "imageUrl": "https://images.unsplash.com/photo-1582719478250-c89cae4dc85b?ixlib=rb-4.0.3&ixid=M3wxMjA3fDB8MHxwaG90by1wYWdlfHx8fGVufDB8fHx8fA%3D%3D&auto=format&fit=crop&w=1000&q=80",
    "createdAt": "2025-08-22T11:23:43.363Z",
    "updatedAt": "2025-08-22T11:46:14.556Z"
  },
  {
    "id": "f71eb151-abda-4758-a5c4-19a1b22d2639",
    "roomNumber": "202",
    "type": "deluxe",
    "price": 399,
    "isBooked": false,
    "guestName": null,
    "checkInDate": null,
    "checkOutDate": null,
    "amenities": [
      "Wi-Fi",
      "TV",
      "Air Conditioning",
      "Mini Bar",
      "Jacuzzi",
      "Balcony",
      "Room Service"
    ],
    "description": "Premium deluxe room with ocean view",
    "imageUrl": "https://images.unsplash.com/photo-1571896349842-33c89424de2d?ixlib=rb-4.0.3&ixid=M3wxMjA3fDB8MHxwaG90by1wYWdlfHx8fGVufDB8fHx8fA%3D%3D&auto=format&fit=crop&w=1000&q=80",
    "createdAt": "2025-08-22T11:23:43.363Z",
    "updatedAt": "2025-08-22T11:23:43.363Z"
  },
  {
    "id": "4a136626-17c8-428e-a3dd-f5ba346ec20f",
    "roomNumber": "103",
    "type": "single",
    "price": 90,
    "isBooked": false,
    "guestName": null,
    "checkInDate": null,
    "checkOutDate": null,
    "amenities": [
      "Wi-Fi",
      "TV",
      "Air Conditioning"
    ],
    "description": "Budget-friendly single room with modern amenities",
    "imageUrl": "https://images.unsplash.com/photo-1631049307264-da0ec9d70304?ixlib=rb-4.0.3&ixid=M3wxMjA3fDB8MHxwaG90by1wYWdlfHx8fGVufDB8fHx8fA%3D%3D&auto=format&fit=crop&w=1000&q=80",
    "createdAt": "2025-08-22T11:40:47.258Z",
    "updatedAt": "2025-08-22T11:40:47.259Z"
  },
  {
    "id": "7b8e4c91-2f5a-4d8e-9b6c-3a1f5e7d9c2b",
    "roomNumber": "104",
    "type": "single",
    "price": 95,
    "isBooked": true,
    "guestName": "Sarah Johnson",
    "checkInDate": "2025-08-24",
    "checkOutDate": "2025-08-26",
    "amenities": [
      "Wi-Fi",
      "TV",
      "Air Conditioning",
      "Coffee Maker"
    ],
    "description": "Cozy single room with workspace area",
    "imageUrl": "https://images.unsplash.com/photo-1566665797739-1674de7a421a?ixlib=rb-4.0.3&ixid=M3wxMjA3fDB8MHxwaG90by1wYWdlfHx8fGVufDB8fHx8fA%3D%3D&auto=format&fit=crop&w=1000&q=80",
    "createdAt": "2025-08-22T12:00:00.000Z",
    "updatedAt": "2025-08-24T09:15:30.123Z"
  },
  {
    "id": "9c3d5e7f-8a1b-4c6d-2e9f-0b4a6c8e1d3f",
    "roomNumber": "105",
    "type": "double",
    "price": 159,
    "isBooked": false,
    "guestName": null,
    "checkInDate": null,
    "checkOutDate": null,
    "amenities": [
      "Wi-Fi",
      "TV",
      "Air Conditioning",
      "Mini Bar",
      "Coffee Maker",
      "Safe"
    ],
    "description": "Modern double room with street view and contemporary furnishings",
    "imageUrl": "https://images.unsplash.com/photo-1590490360182-c33d57733427?ixlib=rb-4.0.3&ixid=M3wxMjA3fDB8MHxwaG90by1wYWdlfHx8fGVufDB8fHx8fA%3D%3D&auto=format&fit=crop&w=1000&q=80",
    "createdAt": "2025-08-22T12:05:00.000Z",
    "updatedAt": "2025-08-22T12:05:00.000Z"
  },
  {
    "id": "2f8a1b4c-6d9e-4f7a-8b5c-9e2d1f3a6b8c",
    "roomNumber": "106",
    "type": "double",
    "price": 169,
    "isBooked": true,
    "guestName": "Michael & Lisa Chen",
    "checkInDate": "2025-08-23",
    "checkOutDate": "2025-08-27",
    "amenities": [
      "Wi-Fi",
      "TV",
      "Air Conditioning",
      "Mini Bar",
      "Coffee Maker",
      "Safe",
      "Bathtub"
    ],
    "description": "Superior double room with marble bathroom and city lights view",
    "imageUrl": "https://images.unsplash.com/photo-1512918728675-ed5a9ecdebfd?ixlib=rb-4.0.3&ixid=M3wxMjA3fDB8MHxwaG90by1wYWdlfHx8fGVufDB8fHx8fA%3D%3D&auto=format&fit=crop&w=1000&q=80",
    "createdAt": "2025-08-22T12:10:00.000Z",
    "updatedAt": "2025-08-23T14:20:15.456Z"
  },
  {
    "id": "8d5b3f1a-4c7e-4a9b-6d2f-5e8a7b3c9d1e",
    "roomNumber": "203",
    "type": "suite",
    "price": 319,
    "isBooked": false,
    "guestName": null,
    "checkInDate": null,
    "checkOutDate": null,
    "amenities": [
      "Wi-Fi",
      "TV",
      "Air Conditioning",
      "Mini Bar",
      "Jacuzzi",
      "Balcony",
      "Living Area",
      "Kitchen"
    ],
    "description": "Executive suite with separate living area and kitchenette",
    "imageUrl": "https://images.unsplash.com/photo-1587985064135-0366536eab42?ixlib=rb-4.0.3&ixid=M3wxMjA3fDB8MHxwaG90by1wYWdlfHx8fGVufDB8fHx8fA%3D%3D&auto=format&fit=crop&w=1000&q=80",
    "createdAt": "2025-08-22T12:15:00.000Z",
    "updatedAt": "2025-08-22T12:15:00.000Z"
  },
  {
    "id": "4e7c2a8f-9b1d-4f3e-7a5c-8b9e4d6f2a1c",
    "roomNumber": "204",
    "type": "suite",
    "price": 339,
    "isBooked": false,
    "guestName": null,
    "checkInDate": null,
    "checkOutDate": null,
    "amenities": [
      "Wi-Fi",
      "TV",
      "Air Conditioning",
      "Mini Bar",
      "Jacuzzi",
      "Balcony",
      "Living Area",
      "Kitchen",
      "Fireplace"
    ],
    "description": "Premium suite with fireplace and panoramic mountain view",
    "imageUrl": "https://images.unsplash.com/photo-1578683010236-d716f9a3f461?ixlib=rb-4.0.3&ixid=M3wxMjA3fDB8MHxwaG90by1wYWdlfHx8fGVufDB8fHx8fA%3D%3D&auto=format&fit=crop&w=1000&q=80",
    "createdAt": "2025-08-22T12:20:00.000Z",
    "updatedAt": "2025-08-22T12:20:00.000Z"
  },
  {
    "id": "7f1a5b8c-3e9d-4c6f-8a2b-5d7e9c1f4a6b",
    "roomNumber": "301",
    "type": "deluxe",
    "price": 419,
    "isBooked": false,
    "guestName": null,
    "checkInDate": null,
    "checkOutDate": null,
    "amenities": [
      "Wi-Fi",
      "TV",
      "Air Conditioning",
      "Mini Bar",
      "Jacuzzi",
      "Balcony",
      "Room Service",
      "Butler Service",
      "Champagne Welcome"
    ],
    "description": "Top floor deluxe room with butler service and champagne welcome",
    "imageUrl": "https://images.unsplash.com/photo-1596394516093-501ba68a0ba6?ixlib=rb-4.0.3&ixid=M3wxMjA3fDB8MHxwaG90by1wYWdlfHx8fGVufDB8fHx8fA%3D%3D&auto=format&fit=crop&w=1000&q=80",
    "createdAt": "2025-08-22T12:25:00.000Z",
    "updatedAt": "2025-08-22T12:25:00.000Z"
  },
  {
    "id": "2c8e4a6f-7b3d-4e9a-5c1f-8d6a9b2e7c4f",
    "roomNumber": "302",
    "type": "deluxe",
    "price": 449,
    "isBooked": true,
    "guestName": "Robert Williams",
    "checkInDate": "2025-08-25",
    "checkOutDate": "2025-08-28",
    "amenities": [
      "Wi-Fi",
      "TV",
      "Air Conditioning",
      "Mini Bar",
      "Jacuzzi",
      "Balcony",
      "Room Service",
      "Butler Service",
      "Champagne Welcome",
      "Private Terrace"
    ],
    "description": "Penthouse deluxe with private terrace and 360-degree city view",
    "imageUrl": "https://images.unsplash.com/photo-1584132967334-10e028bd69f7?ixlib=rb-4.0.3&ixid=M3wxMjA3fDB8MHxwaG90by1wYWdlfHx8fGVufDB8fHx8fA%3D%3D&auto=format&fit=crop&w=1000&q=80",
    "createdAt": "2025-08-22T12:30:00.000Z",
    "updatedAt": "2025-08-25T11:45:22.789Z"
  },
  {
    "id": "9a3f6c1e-5d8b-4c2a-7f9e-1b4c8d5a6e3f",
    "roomNumber": "107",
    "type": "family",
    "price": 199,
    "isBooked": false,
    "guestName": null,
    "checkInDate": null,
    "checkOutDate": null,
    "amenities": [
      "Wi-Fi",
      "TV",
      "Air Conditioning",
      "Mini Bar",
      "Coffee Maker",
      "Safe",
      "Extra Beds",
      "Child-friendly"
    ],
    "description": "Spacious family room with connecting beds and child-safe amenities",
    "imageUrl": "https://images.unsplash.com/photo-1560472354-b33ff0c44a43?ixlib=rb-4.0.3&ixid=M3wxMjA3fDB8MHxwaG90by1wYWdlfHx8fGVufDB8fHx8fA%3D%3D&auto=format&fit=crop&w=1000&q=80",
    "createdAt": "2025-08-22T12:35:00.000Z",
    "updatedAt": "2025-08-22T12:35:00.000Z"
  },
  {
    "id": "6e2d8a4f-9c5b-4e7a-3f1c-7a9b6d2e5c8f",
    "roomNumber": "108",
    "type": "family",
    "price": 219,
    "isBooked": true,
    "guestName": "The Martinez Family",
    "checkInDate": "2025-08-24",
    "checkOutDate": "2025-08-30",
    "amenities": [
      "Wi-Fi",
      "TV",
      "Air Conditioning",
      "Mini Bar",
      "Coffee Maker",
      "Safe",
      "Extra Beds",
      "Child-friendly",
      "Game Console"
    ],
    "description": "Premium family room with game console and pool view",
    "imageUrl": "https://images.unsplash.com/photo-1551882547-ff40c63fe5fa?ixlib=rb-4.0.3&ixid=M3wxMjA3fDB8MHxwaG90by1wYWdlfHx8fGVufDB8fHx8fA%3D%3D&auto=format&fit=crop&w=1000&q=80",
    "createdAt": "2025-08-22T12:40:00.000Z",
    "updatedAt": "2025-08-24T16:30:45.912Z"
  },
  {
    "id": "5c7e9a2d-8b4f-4d6a-2e8c-9f5a7b1d4e6c",
    "roomNumber": "109",
    "type": "accessible",
    "price": 129,
    "isBooked": false,
    "guestName": null,
    "checkInDate": null,
    "checkOutDate": null,
    "amenities": [
      "Wi-Fi",
      "TV",
      "Air Conditioning",
      "Mini Bar",
      "Wheelchair Accessible",
      "Roll-in Shower",
      "Grab Bars",
      "Lowered Fixtures"
    ],
    "description": "Fully accessible room with wheelchair-friendly bathroom and lowered amenities",
    "imageUrl": "https://images.unsplash.com/photo-1595576508898-0ad5c879a061?ixlib=rb-4.0.3&ixid=M3wxMjA3fDB8MHxwaG90by1wYWdlfHx8fGVufDB8fHx8fA%3D%3D&auto=format&fit=crop&w=1000&q=80",
    "createdAt": "2025-08-22T12:45:00.000Z",
    "updatedAt": "2025-08-22T12:45:00.000Z"
  },
  {
    "id": "1f4c7a9e-6d2b-4e8a-9c5f-3a7e1d6b8c4f",
    "roomNumber": "205",
    "type": "presidential",
    "price": 799,
    "isBooked": false,
    "guestName": null,
    "checkInDate": null,
    "checkOutDate": null,
    "amenities": [
      "Wi-Fi",
      "TV",
      "Air Conditioning",
      "Mini Bar",
      "Jacuzzi",
      "Balcony",
      "Room Service",
      "Butler Service",
      "Champagne Welcome",
      "Private Terrace",
      "Dining Room",
      "Office",
      "Private Chef",
      "Limousine Service"
    ],
    "description": "Ultimate presidential suite with private chef, office, and limousine service",
    "imageUrl": "https://images.unsplash.com/photo-1590381105924-c72589b9ef3f?ixlib=rb-4.0.3&ixid=M3wxMjA3fDB8MHxwaG90by1wYWdlfHx8fGVufDB8fHx8fA%3D%3D&auto=format&fit=crop&w=1000&q=80",
    "createdAt": "2025-08-22T12:50:00.000Z",
    "updatedAt": "2025-08-22T12:50:00.000Z"
  },
  {
    "id": "8b5e2c7f-4a9d-4f3c-7e1a-6c8d2f5b9e4a",
    "roomNumber": "110",
    "type": "business",
    "price": 179,
    "isBooked": false,
    "guestName": null,
    "checkInDate": null,
    "checkOutDate": null,
    "amenities": [
      "Wi-Fi",
      "TV",
      "Air Conditioning",
      "Mini Bar",
      "Coffee Maker",
      "Safe",
      "Work Desk",
      "Printer Access",
      "Business Lounge Access"
    ],
    "description": "Business traveler room with dedicated workspace and business lounge access",
    "imageUrl": "https://images.unsplash.com/photo-1591088398332-8a7791972843?ixlib=rb-4.0.3&ixid=M3wxMjA3fDB8MHxwaG90by1wYWdlfHx8fGVufDB8fHx8fA%3D%3D&auto=format&fit=crop&w=1000&q=80",
    "createdAt": "2025-08-22T12:55:00.000Z",
    "updatedAt": "2025-08-22T12:55:00.000Z"
  },
  {
    "id": "3d6a8c2f-7e4b-4a9c-5f2e-8d7a3c6f1b4e",
    "roomNumber": "111",
    "type": "economy",
    "price": 79,
    "isBooked": false,
    "guestName": null,
    "checkInDate": null,
    "checkOutDate": null,
    "amenities": [
      "Wi-Fi",
      "TV",
      "Air Conditioning"
    ],
    "description": "Budget economy room with essential amenities for cost-conscious travelers",
    "imageUrl": "https://images.unsplash.com/photo-1502672260266-1c1ef2d93688?ixlib=rb-4.0.3&ixid=M3wxMjA3fDB8MHxwaG90by1wYWdlfHx8fGVufDB8fHx8fA%3D%3D&auto=format&fit=crop&w=1000&q=80",
    "createdAt": "2025-08-22T13:00:00.000Z",
    "updatedAt": "2025-08-22T13:00:00.000Z"
  },
  {
    "id": "7a9c5f2e-8d4b-4c6a-9e3f-1b8c5d7a2f6e",
    "roomNumber": "206",
    "type": "honeymoon",
    "price": 359,
    "isBooked": true,
    "guestName": "James & Emma Thompson",
    "checkInDate": "2025-08-26",
    "checkOutDate": "2025-08-29",
    "amenities": [
      "Wi-Fi",
      "TV",
      "Air Conditioning",
      "Mini Bar",
      "Jacuzzi",
      "Balcony",
      "Room Service",
      "Rose Petals",
      "Champagne",
      "Romantic Lighting"
    ],
    "description": "Romantic honeymoon suite with rose petals, champagne, and intimate lighting",
    "imageUrl": "https://images.unsplash.com/photo-1564013799919-ab600027ffc6?ixlib=rb-4.0.3&ixid=M3wxMjA3fDB8MHxwaG90by1wYWdlfHx8fGVufDB8fHx8fA%3D%3D&auto=format&fit=crop&w=1000&q=80",
    "createdAt": "2025-08-22T13:05:00.000Z",
    "updatedAt": "2025-08-26T10:20:33.567Z"
  }
]